pysaunum/__init__.py
pysaunum/client.py
pysaunum/const.py
pysaunum/exceptions.py
pysaunum/models.py
pysaunum/py.typed
pysaunum-0.3.0.dist-info/licenses/LICENSE
pysaunum-0.3.0.dist-info/METADATA
pysaunum-0.3.0.dist-info/WHEEL
pysaunum-0.3.0.dist-info/top_level.txt
pysaunum-0.3.0.dist-info/RECORD
