Metadata-Version: 2.4
Name: pysaunum
Version: 0.3.0
Summary: Python library for controlling Saunum sauna controllers via Modbus
Author-email: Mario Mett <mario@mett.ee>
License-Expression: MIT
Project-URL: Homepage, https://github.com/mettolen/pysaunum
Project-URL: Repository, https://github.com/mettolen/pysaunum
Project-URL: Issues, https://github.com/mettolen/pysaunum/issues
Keywords: saunum,sauna,modbus,home-automation
Classifier: Development Status :: 4 - Beta
Classifier: Intended Audience :: Developers
Classifier: Operating System :: OS Independent
Classifier: Programming Language :: Python :: 3
Classifier: Programming Language :: Python :: 3.11
Classifier: Programming Language :: Python :: 3.12
Classifier: Programming Language :: Python :: 3.13
Classifier: Typing :: Typed
Classifier: Topic :: Home Automation
Requires-Python: >=3.11
License-File: LICENSE
Requires-Dist: pymodbus>=3.11.2
Provides-Extra: dev
Requires-Dist: pytest>=7.0; extra == "dev"
Requires-Dist: pytest-asyncio>=0.21.0; extra == "dev"
Requires-Dist: pytest-cov>=4.0; extra == "dev"
Requires-Dist: pytest-timeout>=2.1.0; extra == "dev"
Requires-Dist: ruff>=0.1.0; extra == "dev"
Requires-Dist: mypy>=1.0; extra == "dev"
Dynamic: license-file
